nachomines/__init__.py
nachomines/__main__.py
nachomines/icon.png
nachomines/resources/images/bitmap/MainMenu.png
nachomines/resources/images/bitmap/background.png
nachomines/resources/images/bitmap/chip1.png
nachomines/resources/images/bitmap/chip2.png
nachomines/resources/images/bitmap/flag.png
nachomines/resources/images/bitmap/jalapeno.png
nachomines/resources/images/bitmap/mine.png
nachomines/resources/images/bitmap/mines_cleared.png
nachomines/resources/images/bitmap/spicy_alert.png
nachomines/resources/images/bitmap/you_lost.png
nachomines/resources/sounds/add_flag.wav
nachomines/resources/sounds/boom.wav
nachomines/resources/sounds/click.wav
nachomines/resources/sounds/remove_flag.wav
nachomines/resources/sounds/success.wav
nachomines/scripts/auto_load.py
nachomines/scripts/button.py
nachomines/scripts/get_file.py
nachomines/scripts/main.py
nachomines/scripts/utils.py
nachomines-1.0.4.dist-info/LICENSE
nachomines-1.0.4.dist-info/METADATA
nachomines-1.0.4.dist-info/WHEEL
nachomines-1.0.4.dist-info/entry_points.txt
nachomines-1.0.4.dist-info/top_level.txt
nachomines-1.0.4.dist-info/RECORD
