Metadata-Version: 2.1
Name: nachomines
Version: 1.0.4
Summary: Simple python minesweeper game using pygame
Home-page: https://github.com/nachomonkey/NachoMines
Author: NachoMonkey
License: MIT
Platform: UNKNOWN
Classifier: Programming Language :: Python :: 3 :: Only
Classifier: License :: OSI Approved :: MIT License
Classifier: Operating System :: OS Independent
Classifier: Topic :: Games/Entertainment :: Puzzle Games
Classifier: Development Status :: 5 - Production/Stable
Classifier: Natural Language :: English
Requires-Python: >=3.6
Requires-Dist: setuptools
Requires-Dist: pygame
